async_cache_updater/__init__.py
async_cache_updater/buckets.py
async_cache_updater/cache.py
async_cache_updater/cli.py
async_cache_updater/dateparse.py
async_cache_updater/decorators.py
async_cache_updater/settings.py
async_cache_updater/timezone.py
async_cache_updater/types.py
async_cache_updater/utils.py
async_cache_updater-1.0.0.dist-info/licenses/AUTHORS.rst
async_cache_updater-1.0.0.dist-info/licenses/LICENSE
async_cache_updater-1.0.0.dist-info/METADATA
async_cache_updater-1.0.0.dist-info/WHEEL
async_cache_updater-1.0.0.dist-info/entry_points.txt
async_cache_updater-1.0.0.dist-info/top_level.txt
async_cache_updater-1.0.0.dist-info/RECORD
