Metadata-Version: 2.4
Name: async-cache-updater
Version: 1.0.0
Summary: Caches the output of functions with time-based buckets
Home-page: https://github.com/revpoint/async-cache-updater
Author: RevPoint Media
Author-email: tech@jangl.com
License: MIT license
Keywords: async_cache_updater
Classifier: Development Status :: 2 - Pre-Alpha
Classifier: Intended Audience :: Developers
Classifier: License :: OSI Approved :: MIT License
Classifier: Natural Language :: English
Classifier: Programming Language :: Python :: 3
Classifier: Programming Language :: Python :: 3.9
Classifier: Programming Language :: Python :: 3.10
Classifier: Programming Language :: Python :: 3.11
Classifier: Programming Language :: Python :: 3.12
Classifier: Programming Language :: Python :: 3.13
Requires-Python: >=3.9
License-File: LICENSE
License-File: AUTHORS.rst
Requires-Dist: redis
Requires-Dist: asgiref
Requires-Dist: hiredis
Requires-Dist: python-dateutil
Requires-Dist: pytz
Dynamic: author
Dynamic: author-email
Dynamic: classifier
Dynamic: description
Dynamic: home-page
Dynamic: keywords
Dynamic: license
Dynamic: license-file
Dynamic: requires-dist
Dynamic: requires-python
Dynamic: summary
